[
  {
    "randomSeed": 1,
    "gridMin": {
      "x": 0,
      "y": 0
    },
    "gridMax": {
      "x": 10,
      "y": 10
    },
    "tileSize": 1.05,
    "nbPit": 3,
    "nbWumpus": 3,
    "nbGold": 1,
    "nbAgent": 1,
    "aiType": "Prolog",
    "personalities": [
      3,
      2
    ],
    "agents": 1,
    "isGameOver": true,
    "isModeAuto": true,
    "turnDuration": [
      10.68,
      10.30,
      8.70,
      9.18,
      11.72,
      10.77,
      11.61,
      10.51,
      11.38,
      10.94,
      11.87,
      11.47,
      11.53,
      12.75,
      13.79,
      13.76,
      14.02,
      10.51,
      14.18,
      13.79,
      15.56,
      14.92,
      12.25,
      15.09,
      15.60,
      14.70,
      15.69,
      16.84,
      16.38,
      14.04,
      17.22,
      16.13,
      15.51,
      17.38,
      17.41,
      15.28,
      16.68,
      17.24,
      17.65,
      18.08,
      18.05,
      17.00,
      18.57,
      18.88,
      17.27,
      19.00,
      18.59,
      17.02,
      19.55,
      19.97,
      19.38,
      18.61,
      20.55,
      19.98,
      22.09,
      18.87,
      20.04,
      19.14,
      20.37,
      19.01,
      20.22,
      19.67,
      21.05,
      20.90,
      20.37,
      21.34,
      21.25,
      21.04,
      21.01,
      21.94,
      21.84,
      21.51,
      21.19,
      22.78,
      21.57,
      22.22,
      21.24,
      21.81,
      22.13,
      21.47,
      22.70,
      22.03,
      24.66,
      26.49,
      22.07,
      25.39,
      25.21,
      24.53,
      22.29,
      25.30,
      24.69,
      25.28,
      26.26,
      30.43,
      29.02,
      27.64,
      26.77,
      27.74,
      29.21,
      27.29,
      30.08,
      27.92,
      28.22,
      30.96,
      28.82,
      26.60,
      30.41,
      28.12,
      30.85,
      33.16,
      27.92,
      30.05,
      31.72,
      29.13,
      31.61
    ]
  },
  {
    "agent": "human0",
    "actions": [
      "MoveRight",
      "MoveRight",
      "MoveBack",
      "MoveUp",
      "MoveRight",
      "MoveBack",
      "MoveLeft",
      "MoveLeft",
      "MoveLeft",
      "MoveLeft",
      "MoveBack",
      "MoveUp",
      "MoveRight",
      "MoveRight",
      "MoveRight",
      "MoveRight",
      "MoveRight",
      "MoveBack",
      "MoveUp",
      "MoveRight",
      "MoveRight",
      "MoveRight",
      "MoveBack",
      "MoveUp",
      "MoveRight",
      "MoveBack",
      "MoveLeft",
      "MoveBack",
      "MoveUp",
      "MoveBack",
      "MoveBack",
      "MoveDown",
      "MoveBack",
      "MoveBack",
      "MoveBack",
      "MoveLeft",
      "MoveLeft",
      "MoveLeft",
      "MoveLeft",
      "MoveLeft",
      "MoveBack",
      "MoveUp",
      "MoveRight",
      "MoveBack",
      "MoveLeft",
      "MoveBack",
      "MoveUp",
      "MoveBack",
      "MoveBack",
      "MoveBack",
      "MoveBack",
      "MoveUp",
      "MoveRight",
      "MoveRight",
      "MoveUp",
      "MoveBack",
      "MoveBack",
      "MoveUp",
      "MoveLeft",
      "MoveBack",
      "MoveUp",
      "MoveBack",
      "MoveBack",
      "MoveBack",
      "MoveBack",
      "MoveBack",
      "MoveBack",
      "MoveBack",
      "MoveBack",
      "MoveBack",
      "MoveBack",
      "MoveBack",
      "MoveLeft",
      "MoveBack",
      "MoveBack",
      "MoveDown",
      "MoveRight",
      "MoveDown",
      "MoveRight",
      "MoveRight",
      "MoveBack",
      "MoveDown",
      "MoveRight",
      "MoveRight",
      "MoveBack",
      "MoveDown",
      "MoveBack",
      "MoveBack",
      "MoveLeft",
      "MoveLeft",
      "MoveLeft",
      "MoveBack",
      "MoveUp",
      "MoveLeft",
      "MoveBack",
      "MoveBack",
      "MoveDown",
      "MoveBack",
      "MoveBack",
      "MoveDown",
      "MoveBack",
      "MoveBack",
      "MoveDown",
      "MoveBack",
      "MoveBack",
      "MoveBack",
      "MoveBack",
      "MoveBack",
      "MoveLeft",
      "MoveBack",
      "MoveBack",
      "MoveBack",
      "MoveBack",
      "MoveBack",
      "MoveBack"
    ],
    "positions": [
      {
        "x": 4,
        "y": 3
      },
      {
        "x": 5,
        "y": 3
      },
      {
        "x": 4,
        "y": 3
      },
      {
        "x": 4,
        "y": 4
      },
      {
        "x": 5,
        "y": 4
      },
      {
        "x": 4,
        "y": 4
      },
      {
        "x": 3,
        "y": 4
      },
      {
        "x": 2,
        "y": 4
      },
      {
        "x": 1,
        "y": 4
      },
      {
        "x": 0,
        "y": 4
      },
      {
        "x": 1,
        "y": 4
      },
      {
        "x": 1,
        "y": 5
      },
      {
        "x": 2,
        "y": 5
      },
      {
        "x": 3,
        "y": 5
      },
      {
        "x": 4,
        "y": 5
      },
      {
        "x": 5,
        "y": 5
      },
      {
        "x": 6,
        "y": 5
      },
      {
        "x": 5,
        "y": 5
      },
      {
        "x": 5,
        "y": 6
      },
      {
        "x": 6,
        "y": 6
      },
      {
        "x": 7,
        "y": 6
      },
      {
        "x": 8,
        "y": 6
      },
      {
        "x": 7,
        "y": 6
      },
      {
        "x": 7,
        "y": 7
      },
      {
        "x": 8,
        "y": 7
      },
      {
        "x": 7,
        "y": 7
      },
      {
        "x": 6,
        "y": 7
      },
      {
        "x": 7,
        "y": 7
      },
      {
        "x": 7,
        "y": 8
      },
      {
        "x": 7,
        "y": 7
      },
      {
        "x": 7,
        "y": 6
      },
      {
        "x": 7,
        "y": 5
      },
      {
        "x": 7,
        "y": 6
      },
      {
        "x": 6,
        "y": 6
      },
      {
        "x": 5,
        "y": 6
      },
      {
        "x": 4,
        "y": 6
      },
      {
        "x": 3,
        "y": 6
      },
      {
        "x": 2,
        "y": 6
      },
      {
        "x": 1,
        "y": 6
      },
      {
        "x": 0,
        "y": 6
      },
      {
        "x": 1,
        "y": 6
      },
      {
        "x": 1,
        "y": 7
      },
      {
        "x": 2,
        "y": 7
      },
      {
        "x": 1,
        "y": 7
      },
      {
        "x": 0,
        "y": 7
      },
      {
        "x": 1,
        "y": 7
      },
      {
        "x": 1,
        "y": 8
      },
      {
        "x": 1,
        "y": 7
      },
      {
        "x": 1,
        "y": 6
      },
      {
        "x": 2,
        "y": 6
      },
      {
        "x": 3,
        "y": 6
      },
      {
        "x": 3,
        "y": 7
      },
      {
        "x": 4,
        "y": 7
      },
      {
        "x": 5,
        "y": 7
      },
      {
        "x": 5,
        "y": 8
      },
      {
        "x": 5,
        "y": 7
      },
      {
        "x": 4,
        "y": 7
      },
      {
        "x": 4,
        "y": 8
      },
      {
        "x": 3,
        "y": 8
      },
      {
        "x": 4,
        "y": 8
      },
      {
        "x": 4,
        "y": 9
      },
      {
        "x": 4,
        "y": 8
      },
      {
        "x": 4,
        "y": 7
      },
      {
        "x": 3,
        "y": 7
      },
      {
        "x": 3,
        "y": 6
      },
      {
        "x": 4,
        "y": 6
      },
      {
        "x": 5,
        "y": 6
      },
      {
        "x": 5,
        "y": 5
      },
      {
        "x": 4,
        "y": 5
      },
      {
        "x": 3,
        "y": 5
      },
      {
        "x": 2,
        "y": 5
      },
      {
        "x": 1,
        "y": 5
      },
      {
        "x": 0,
        "y": 5
      },
      {
        "x": 1,
        "y": 5
      },
      {
        "x": 1,
        "y": 4
      },
      {
        "x": 1,
        "y": 3
      },
      {
        "x": 2,
        "y": 3
      },
      {
        "x": 2,
        "y": 2
      },
      {
        "x": 3,
        "y": 2
      },
      {
        "x": 4,
        "y": 2
      },
      {
        "x": 3,
        "y": 2
      },
      {
        "x": 3,
        "y": 1
      },
      {
        "x": 4,
        "y": 1
      },
      {
        "x": 5,
        "y": 1
      },
      {
        "x": 4,
        "y": 1
      },
      {
        "x": 4,
        "y": 0
      },
      {
        "x": 4,
        "y": 1
      },
      {
        "x": 3,
        "y": 1
      },
      {
        "x": 2,
        "y": 1
      },
      {
        "x": 1,
        "y": 1
      },
      {
        "x": 0,
        "y": 1
      },
      {
        "x": 1,
        "y": 1
      },
      {
        "x": 1,
        "y": 2
      },
      {
        "x": 0,
        "y": 2
      },
      {
        "x": 1,
        "y": 2
      },
      {
        "x": 1,
        "y": 1
      },
      {
        "x": 1,
        "y": 0
      },
      {
        "x": 1,
        "y": 1
      },
      {
        "x": 2,
        "y": 1
      },
      {
        "x": 2,
        "y": 0
      },
      {
        "x": 2,
        "y": 1
      },
      {
        "x": 3,
        "y": 1
      },
      {
        "x": 3,
        "y": 0
      },
      {
        "x": 3,
        "y": 1
      },
      {
        "x": 3,
        "y": 2
      },
      {
        "x": 2,
        "y": 2
      },
      {
        "x": 2,
        "y": 3
      },
      {
        "x": 1,
        "y": 3
      },
      {
        "x": 0,
        "y": 3
      },
      {
        "x": 1,
        "y": 3
      },
      {
        "x": 1,
        "y": 4
      },
      {
        "x": 2,
        "y": 4
      },
      {
        "x": 3,
        "y": 4
      },
      {
        "x": 4,
        "y": 4
      },
      {
        "x": 4,
        "y": 3
      }
    ]
  }
]